django_profiler/__init__.py
django_profiler/middleware.py
django_profiler_middleware-1.0.dist-info/DESCRIPTION.rst
django_profiler_middleware-1.0.dist-info/METADATA
django_profiler_middleware-1.0.dist-info/metadata.json
django_profiler_middleware-1.0.dist-info/RECORD
django_profiler_middleware-1.0.dist-info/top_level.txt
django_profiler_middleware-1.0.dist-info/WHEEL
profiler/__init__.py
profiler/middleware.py
