Metadata-Version: 1.1
Name: django-profiler-middleware
Version: 1.0
Summary: A profiler middleware for Django
Home-page: https://github.com/mysociety/django-profiler-middleware
Author: mySociety
Author-email: matthew@mysociety.org
License: UNKNOWN
Platform: UNKNOWN
Classifier: Development Status :: 5 - Production/Stable
Classifier: Environment :: Web Environment
Classifier: Framework :: Django
Classifier: License :: OSI Approved :: BSD License
Classifier: Intended Audience :: Developers
Classifier: Programming Language :: Python
Classifier: Topic :: Database :: Front-Ends
Classifier: Topic :: Internet :: WWW/HTTP
